<annotation>
<folder>FeministArt</folder>
<style>FeministArt</style>
<filename>kiki-smith_wolf-girl-1999.jpg</filename>
<source>
	<database>art_person_v1</database>
	<annotation>art_person_v1</annotation>
	<image>wikipaintings</image>
	<flickrid>0</flickrid>
</source>
<owner>
	<flickrid>0</flickrid>
	<name>kiki-smith</name>
</owner>
<size>
	<width>370</width>
	<height>500</height>
	<depth>3</depth>
</size>
<segmented>0</segmented>
<difficult>0</difficult>
<object>
	<pose>Frontal</pose>
	<truncated>1</truncated>
	<difficult>0</difficult>
	<name>person</name>
	<bndbox>
		<xmin>2</xmin>
		<ymin>26</ymin>
		<xmax>370</xmax>
		<ymax>500</ymax>
	</bndbox>
</object>
</annotation>
