<annotation>
<folder>NorthernRenaissance</folder>
<style>NorthernRenaissance</style>
<filename>albrecht-durer_title-page-to-the-second-latin-edition-of-1511-1498.jpg</filename>
<source>
	<database>art_person_v1</database>
	<annotation>art_person_v1</annotation>
	<image>wikipaintings</image>
	<flickrid>0</flickrid>
</source>
<owner>
	<flickrid>0</flickrid>
	<name>albrecht-durer</name>
</owner>
<size>
	<width>321</width>
	<height>500</height>
	<depth>1</depth>
</size>
<segmented>0</segmented>
<difficult>0</difficult>
<object>
	<pose>Frontal</pose>
	<truncated>1</truncated>
	<difficult>0</difficult>
	<name>person</name>
	<bndbox>
		<xmin>88</xmin>
		<ymin>310</ymin>
		<xmax>192</xmax>
		<ymax>469</ymax>
	</bndbox>
</object>
<object>
	<pose>Left</pose>
	<truncated>1</truncated>
	<difficult>0</difficult>
	<name>person</name>
	<bndbox>
		<xmin>203</xmin>
		<ymin>242</ymin>
		<xmax>295</xmax>
		<ymax>413</ymax>
	</bndbox>
</object>
<object>
	<pose>Right</pose>
	<truncated>1</truncated>
	<difficult>0</difficult>
	<name>person</name>
	<bndbox>
		<xmin>214</xmin>
		<ymin>280</ymin>
		<xmax>253</xmax>
		<ymax>344</ymax>
	</bndbox>
</object>
</annotation>
