<annotation>
<folder>NorthernRenaissance</folder>
<style>NorthernRenaissance</style>
<filename>albrecht-altdorfer_wild-folk-family-1510.jpg</filename>
<source>
	<database>art_person_v1</database>
	<annotation>art_person_v1</annotation>
	<image>wikipaintings</image>
	<flickrid>0</flickrid>
</source>
<owner>
	<flickrid>0</flickrid>
	<name>albrecht-altdorfer</name>
</owner>
<size>
	<width>366</width>
	<height>500</height>
	<depth>3</depth>
</size>
<segmented>0</segmented>
<difficult>1</difficult>
</annotation>
