<annotation>
<folder>AnalyticalRealism</folder>
<style>AnalyticalRealism</style>
<filename>pavel-filonov_selfportrait-1925.jpg</filename>
<source>
	<database>art_person_v2</database>
	<annotation>art_person_v2</annotation>
	<image>wikipaintings</image>
	<flickrid>0</flickrid>
</source>
<owner>
	<flickrid>0</flickrid>
	<name>pavel-filonov</name>
</owner>
<size>
	<width>370</width>
	<height>500</height>
	<depth>3</depth>
</size>
<segmented>0</segmented>
<difficult>0</difficult>
<object>
	<pose>Left</pose>
	<truncated>1</truncated>
	<difficult>0</difficult>
	<name>person</name>
	<bndbox>
		<xmin>62</xmin>
		<ymin>10</ymin>
		<xmax>362</xmax>
		<ymax>492</ymax>
	</bndbox>
</object>
</annotation>
