<annotation>
<folder>PopArt</folder>
<style>PopArt</style>
<filename>walter-battiss_horse-and-butterfly.jpg</filename>
<source>
	<database>art_person_v1</database>
	<annotation>art_person_v1</annotation>
	<image>wikipaintings</image>
	<flickrid>0</flickrid>
</source>
<owner>
	<flickrid>0</flickrid>
	<name>walter-battiss</name>
</owner>
<size>
	<width>500</width>
	<height>376</height>
	<depth>3</depth>
</size>
<segmented>0</segmented>
<difficult>0</difficult>
<object>
	<pose>Right</pose>
	<truncated>1</truncated>
	<difficult>0</difficult>
	<name>person</name>
	<bndbox>
		<xmin>357</xmin>
		<ymin>64</ymin>
		<xmax>453</xmax>
		<ymax>368</ymax>
	</bndbox>
</object>
<object>
	<pose>Left</pose>
	<truncated>1</truncated>
	<difficult>0</difficult>
	<name>person</name>
	<bndbox>
		<xmin>393</xmin>
		<ymin>65</ymin>
		<xmax>477</xmax>
		<ymax>369</ymax>
	</bndbox>
</object>
<object>
	<pose>Lying</pose>
	<truncated>0</truncated>
	<difficult>0</difficult>
	<name>person</name>
	<bndbox>
		<xmin>21</xmin>
		<ymin>93</ymin>
		<xmax>304</xmax>
		<ymax>202</ymax>
	</bndbox>
</object>
<object>
	<pose>Lying</pose>
	<truncated>0</truncated>
	<difficult>0</difficult>
	<name>person</name>
	<bndbox>
		<xmin>30</xmin>
		<ymin>107</ymin>
		<xmax>341</xmax>
		<ymax>190</ymax>
	</bndbox>
</object>
<object>
	<pose>Lying</pose>
	<truncated>0</truncated>
	<difficult>0</difficult>
	<name>person</name>
	<bndbox>
		<xmin>49</xmin>
		<ymin>206</ymin>
		<xmax>335</xmax>
		<ymax>320</ymax>
	</bndbox>
</object>
<object>
	<pose>Lying</pose>
	<truncated>0</truncated>
	<difficult>0</difficult>
	<name>person</name>
	<bndbox>
		<xmin>55</xmin>
		<ymin>224</ymin>
		<xmax>327</xmax>
		<ymax>315</ymax>
	</bndbox>
</object>
</annotation>
