<annotation>
<folder>ArtNouveau(Modern)</folder>
<style>ArtNouveau(Modern)</style>
<filename>heorhiy-narbut_illustration-to-wooden-eagle-1909.jpg</filename>
<source>
	<database>art_person_v1</database>
	<annotation>art_person_v1</annotation>
	<image>wikipaintings</image>
	<flickrid>0</flickrid>
</source>
<owner>
	<flickrid>0</flickrid>
	<name>heorhiy-narbut</name>
</owner>
<size>
	<width>393</width>
	<height>500</height>
	<depth>3</depth>
</size>
<segmented>0</segmented>
<difficult>0</difficult>
<object>
	<pose>Left</pose>
	<truncated>0</truncated>
	<difficult>0</difficult>
	<name>person</name>
	<bndbox>
		<xmin>143</xmin>
		<ymin>92</ymin>
		<xmax>199</xmax>
		<ymax>235</ymax>
	</bndbox>
</object>
</annotation>
